{
  "id": "nvidia_inception",
  "titulo": "Inception Program for Startups | NVIDIA",
  "nome_produto": "NVIDIA Inception",
  "categoria": "programa_startups",
  "conteudo": "NVIDIA Inception program.\n\nWhat Is NVIDIA Inception?\n\nInception is a free program that guides AI startups through the NVIDIA platform and ecosystem. From prototype to production, Inception meets you where you are, with member benefits to help you discover new AI opportunities, build with world-class technologies, and grow your business.\n\n!YouTube Video\n\nProgram Benefits\n\nInception members have access to the latest developer tools and training, preferred pricing on NVIDIA hardware and software, exclusive offers from partners, and exposure to a global ecosystem of investors.\n\nTraining and Guidance\n\nHone critical skills with free self-paced technical courses and discounted expert-led workshops.\nDiscover the best tools and resources for your work with personalized recommendations.\nFind answers to technical questions fast with full access to NVIDIA Developer Forums.\nHear about new product releases and members-only offers in Inception’s monthly newsletter.\n\nDeveloper Tools and Offers\n\nTackle AI challenges with the latest SDKs, model libraries, and developer platforms.\nBuild with world-class technology with preferred pricing on select NVIDIA hardware and software.\nDevelop AI applications faster with exclusive partner offers on tools, services, and support.\nAccess free cloud credits from NVIDIA and partners for more flexible, scalable development and deployment.\n\nInvestor Access\n\nGet exposure to the investors in NVIDIA’s extensive VC network through Inception Capital Connect (based on eligibility).\nJoin curated networking events that bring together startups, top VCs, and NVIDIA executives.\n\nBrand and Market Reach\n\nAmplify your brand with official badges, co-branded social content, and customizable assets for events.\nTap into NVIDIA’s global networks through world-class events and strategic introductions.\nUnlock go-to-market and other business opportunities as your engagement with NVIDIA grows.\n\nGet Started\n\nYou can apply to the NVIDIA Inception program regardless of your company’s current funding stage. There are no application fees, deadlines, or cohorts.\n\nApply to Inception\n\nSubmit an application with details about your business and products. We’ll reach out with more information after we review your application.\n\nUpdate Your Profile\n\nKeep your profile up to date to get personalized recommendations and hear about new opportunities from NVIDIA that are right for you.\n\nExplore Your Benefits\n\nAccess exclusive program benefits designed to help you discover new AI opportunities, build faster, and grow your business.\n\nApply Now\n\nMember Spotlight Stories\n\nANYbotics\n\nANYbotics Is Revolutionizing Industrial Inspection With AI\n\nANYbotics’ AI-powered autonomous robots navigate complex environments, capturing vital visual, thermal, and acoustic data to boost safety and productivity.\n\nWatch Video\n\nMoon Surgical\n\nMoon Surgical Is Collaborating With NVIDIA to Advance Robotic Surgery\n\nAI and simulation technologies are enabling new possibilities in robotic surgery through NVIDIA Isaac™ for Healthcare, driving innovation in minimally invasive procedures for patients.\n\nSana\n\nSana Is Pioneering the Next Generation of Knowledge Tools With AI\n\nIn today’s enterprises, knowledge is scattered across countless apps. Sana’s AI-accelerated platform unifies company data into one intuitive interface—making information accessible, actionable, and ready for the next billion users.\n\nEmerald AI\n\nAI Factories Are Becoming Flexible With Emerald AI and NVIDIA\n\nEmerald AI enables data centers to adapt energy use in real time, making advanced AI infrastructure more sustainable and reliable. This flexible energy management also accelerates new data center deployment, prevents blackouts, and supports clean energy integration.\n\nRead Blog\n\nIguazio\n\nBuild Scalable and Observable AI Ready for Production With Iguazio and NVIDIA\n\nIguazio’s MLRun automates the deployment of NVIDIA NIM™ microservices for AI inference across different environments, ensuring efficient operations. Together, they make AI deployment and management faster, more scalable, and capable of handling complex workloads.\n\nVortex Imaging\n\nVortex Delivers CT-Like Ultrasound to Doctors With NVIDIA Jetson\n\nVortex Imaging is making high-quality medical imaging more accessible and effective by using NVIDIA® Jetson™ and TensorRT™ to produce CT-like ultrasound images with edge AI and cloud-based GPU reconstruction. This technology brings advanced imaging to the point of care, improving diagnostic accuracy and patient outcomes.\n\nExplore More\n\nInception Startup Showcase\n\nSee how Inception helps startups discover their AI opportunity, build world-class products, and grow their business.\n\nExplore Stories\n\nInception at Events\n\nOctober 13–16** | Oracle AI WorldLas Vegas, Nevada |\nOctober 27–29** | NVIDIA GTCWashington, D.C. |\nNovember 10–13** | KubeConAtlanta, Georgia |\nNovember 16–21** | SupercomputingSt. Louis, Missouri |\nNovember 18-21** | Microsoft IgniteSan Francisco, California |\nDecember 1–5** | AWS Re:InventLas Vegas, Nevada |\nDecember 2-7** | NeurIPSSan Diego, California |\n\nShow Less\n\nConnect With Top VC Firms\n\nThe NVIDIA Inception VC Alliance helps eligible startups connect with a global ecosystem of top-tier VC firms.\n\nExplore Now\n\nMeet the Startups Shaping Tomorrow’s AI\n\nBehind every great innovation is a story worth sharing. Step inside the worlds of startups that are changing our lives every day with AI. Dive into their journeys, explore their technologies, and discover how NVIDIA helps visionaries turn bold ideas into reality. The NVIDIA Inception Startup Showcase is your front-row seat to the future.\n\nOne Portal. Endless Possibilities.\n\nThe Inception portal is your personalized hub for everything you need to accelerate AI innovation. Access training recommendations, technical resources, and content designed for startups like yours. Request members-only benefits like preferred pricing on NVIDIA hardware and software, free cloud credits from our partners, and technical training for your team. Stay connected, explore community activities, and tap into the latest program offers—all on one easy-to-use platform.\n\nEnter Portal\n\nNVIDIA Connect Program for ISVs\n\nNot a startup? NVIDIA Connect is a free program that helps software development companies and service providers shorten time to market through tailored development resources, technical training and guidance, and preferred pricing on NVIDIA technologies.\n\nLearn More\n\nWorking With VC Firms\n\nDiscover how Inception collaborates with NVIDIA VC Alliance, a global network of AI and technology investors, to support the world’s most innovative startups. Through VC Alliance, NVIDIA helps investors maximize portfolio performance by providing domain expertise and the resources portfolio companies need to succeed.\n\nJoin NVIDIA Inception Today\n\nGet the Latest Startup News\n\nSubscribe",
  "url_pesquisa": "https://www.nvidia.com/en-us/startups/",
  "tags": [
    "startups",
    "programa",
    "beneficios",
    "go-to-market"
  ],
  "caso_uso": [
    "aceleracao de startups",
    "beneficios comerciais e tecnicos"
  ],
  "fonte_tipo": "official_program",
  "coletado_em": "2026-06-29T20:34:58.906129+00:00"
}